aliyunsdkdbfs/__init__.py
aliyunsdkdbfs/endpoint.py
aliyunsdkdbfs/request/__init__.py
aliyunsdkdbfs/request/v20200418/AddTagsBatchRequest.py
aliyunsdkdbfs/request/v20200418/ApplyAutoSnapshotPolicyRequest.py
aliyunsdkdbfs/request/v20200418/AttachDbfsRequest.py
aliyunsdkdbfs/request/v20200418/CancelAutoSnapshotPolicyRequest.py
aliyunsdkdbfs/request/v20200418/CreateAutoSnapshotPolicyRequest.py
aliyunsdkdbfs/request/v20200418/CreateDbfsRequest.py
aliyunsdkdbfs/request/v20200418/CreateServiceLinkedRoleRequest.py
aliyunsdkdbfs/request/v20200418/CreateSnapshotRequest.py
aliyunsdkdbfs/request/v20200418/DeleteAutoSnapshotPolicyRequest.py
aliyunsdkdbfs/request/v20200418/DeleteDbfsRequest.py
aliyunsdkdbfs/request/v20200418/DeleteSnapshotRequest.py
aliyunsdkdbfs/request/v20200418/DeleteTagsBatchRequest.py
aliyunsdkdbfs/request/v20200418/DescribeDbfsSpecificationsRequest.py
aliyunsdkdbfs/request/v20200418/DescribeInstanceTypesRequest.py
aliyunsdkdbfs/request/v20200418/DetachDbfsRequest.py
aliyunsdkdbfs/request/v20200418/GetAutoSnapshotPolicyRequest.py
aliyunsdkdbfs/request/v20200418/GetDbfsRequest.py
aliyunsdkdbfs/request/v20200418/GetServiceLinkedRoleRequest.py
aliyunsdkdbfs/request/v20200418/GetSnapshotLinkRequest.py
aliyunsdkdbfs/request/v20200418/ListAutoSnapshotPoliciesRequest.py
aliyunsdkdbfs/request/v20200418/ListAutoSnapshotPolicyAppliedDbfsRequest.py
aliyunsdkdbfs/request/v20200418/ListAutoSnapshotPolicyUnappliedDbfsRequest.py
aliyunsdkdbfs/request/v20200418/ListDbfsAttachableEcsInstancesRequest.py
aliyunsdkdbfs/request/v20200418/ListDbfsAttachedEcsInstancesRequest.py
aliyunsdkdbfs/request/v20200418/ListDbfsRequest.py
aliyunsdkdbfs/request/v20200418/ListSnapshotLinksRequest.py
aliyunsdkdbfs/request/v20200418/ListSnapshotRequest.py
aliyunsdkdbfs/request/v20200418/ListTagKeysRequest.py
aliyunsdkdbfs/request/v20200418/ListTagValuesRequest.py
aliyunsdkdbfs/request/v20200418/ModifyAutoSnapshotPolicyRequest.py
aliyunsdkdbfs/request/v20200418/ModifySnapshotAttributeRequest.py
aliyun_python_sdk_dbfs-2.0.7.dist-info/LICENSE
aliyun_python_sdk_dbfs-2.0.7.dist-info/METADATA
aliyun_python_sdk_dbfs-2.0.7.dist-info/WHEEL
aliyun_python_sdk_dbfs-2.0.7.dist-info/top_level.txt
aliyun_python_sdk_dbfs-2.0.7.dist-info/RECORD
